setup.py
demodistributions/Binomialdistribution.py
demodistributions/Gaussiandistribution.py
demodistributions/Generaldistribution.py
demodistributions/__init__.py
demodistributions.egg-info/PKG-INFO
demodistributions.egg-info/SOURCES.txt
demodistributions.egg-info/dependency_links.txt
demodistributions.egg-info/not-zip-safe
demodistributions.egg-info/top_level.txt