Metadata-Version: 1.0
Name: demodistributions
Version: 0.1
Summary: Gaussian distributions
Home-page: UNKNOWN
Author: Tousifahamed
Author-email: UNKNOWN
License: UNKNOWN
Platform: UNKNOWN
